gcloud/py.typed
gcloud/rest/py.typed
gcloud/rest/storage/__init__.py
gcloud/rest/storage/blob.py
gcloud/rest/storage/bucket.py
gcloud/rest/storage/constants.py
gcloud/rest/storage/py.typed
gcloud/rest/storage/storage.py
gcloud_rest_storage-9.6.1.dist-info/METADATA
gcloud_rest_storage-9.6.1.dist-info/WHEEL
gcloud_rest_storage-9.6.1.dist-info/licenses/LICENSE
gcloud_rest_storage-9.6.1.dist-info/RECORD
