Metadata-Version: 2.4
Name: gcloud-rest-storage
Version: 9.6.1
Summary: Python Client for Google Cloud Storage
License: MIT
License-File: LICENSE
Author: Vi Engineering
Author-email: voiceai-eng@dialpad.com
Requires-Python: >=3.9,<4.0
Classifier: Development Status :: 5 - Production/Stable
Classifier: Intended Audience :: Developers
Classifier: License :: OSI Approved :: MIT License
Classifier: Operating System :: OS Independent
Classifier: Programming Language :: Python :: 3
Classifier: Programming Language :: Python :: 3.9
Classifier: Programming Language :: Python :: 3.10
Classifier: Programming Language :: Python :: 3.11
Classifier: Programming Language :: Python :: 3.12
Classifier: Programming Language :: Python :: 3.13
Classifier: Programming Language :: Python :: 3.14
Classifier: Topic :: Internet
Requires-Dist: gcloud-rest-auth (>=5.3.0,<6.0.0)
Requires-Dist: pyasn1-modules (>=0.2.1,<0.5.0)
Requires-Dist: rsa (>=3.1.4,<5.0.0)
Project-URL: Repository, https://github.com/talkiq/gcloud-aio
